recaptcha_works
