Metadata-Version: 1.0
Name: django-recaptcha-works
Version: 0.3.4
Summary: django-recaptcha-works provides a Django form field that integrates the reCaptcha service.
Home-page: http://www.codetrax.org/projects/django-recaptcha-works
Author: George Notaras
Author-email: gnot [at] g-loaded.eu
License: BSD License
Download-URL: https://source.codetrax.org/hgroot/django-recaptcha-works
Platform: UNKNOWN
Classifier: Development Status :: 4 - Beta
Classifier: Environment :: Web Environment
Classifier: Framework :: Django
Classifier: Intended Audience :: Developers
Classifier: License :: OSI Approved :: BSD License
Classifier: Natural Language :: English
Classifier: Operating System :: OS Independent
Classifier: Programming Language :: Python
Classifier: Topic :: Internet :: WWW/HTTP :: Dynamic Content
Classifier: Topic :: Software Development :: Libraries :: Application Frameworks
Classifier: Topic :: Software Development :: Libraries :: Python Modules
